ref_man_py/__init__.py
ref_man_py/__main__.py
ref_man_py/arxiv.py
ref_man_py/config.py
ref_man_py/const.py
ref_man_py/cvf.py
ref_man_py/data.py
ref_man_py/dblp.py
ref_man_py/pdf_cache.py
ref_man_py/py.typed
ref_man_py/q_helper.py
ref_man_py/service.py
ref_man_py/util.py
ref_man_py-0.8.0.dist-info/LICENSE.md
ref_man_py-0.8.0.dist-info/METADATA
ref_man_py-0.8.0.dist-info/WHEEL
ref_man_py-0.8.0.dist-info/entry_points.txt
ref_man_py-0.8.0.dist-info/RECORD
