Metadata-Version: 2.1
Name: ref-man-py
Version: 0.8.0
Summary: Ref Man Python Module
Home-page: https://github.com/akshaybadola/ref-man-py
License: MIT
Keywords: emacs,semanticscholar,bibliography,ref-man
Author: Akshay
Author-email: akshay.badola.cs@gmail.com
Requires-Python: >=3.8,<4.0
Classifier: Development Status :: 4 - Beta
Classifier: Intended Audience :: Science/Research
Classifier: License :: OSI Approved :: MIT License
Classifier: Natural Language :: English
Classifier: Programming Language :: Python :: 3
Classifier: Programming Language :: Python :: 3.8
Classifier: Programming Language :: Python :: 3.9
Classifier: Programming Language :: Python :: 3.10
Classifier: Programming Language :: Python :: 3.11
Classifier: Programming Language :: Python :: 3.12
Classifier: Programming Language :: Python :: 3.7
Classifier: Topic :: Education
Classifier: Topic :: Scientific/Engineering
Classifier: Topic :: Text Editors :: Emacs
Requires-Dist: MarkupSafe (==2.0.1)
Requires-Dist: PyYAML (>=6.0.0,<7.0.0)
Requires-Dist: aiohttp (>=3.8.1,<4.0.0)
Requires-Dist: beautifulsoup4 (>=4.9.1,<5.0.0)
Requires-Dist: common_pyutil (>=0.8.5,<1.0.0)
Requires-Dist: file-magic (>=0.4.1,<0.5.0)
Requires-Dist: flask (>=1.1.2,<2.0.0)
Requires-Dist: lxml (>=4.6.4,<5.0.0)
Requires-Dist: psutil (>=5.8.0,<6.0.0)
Requires-Dist: requests (>=2.31.0,<3.0.0)
Requires-Dist: s2cache (>=0.3.9,<0.4.0)
